tech_smu_mcp_demo/__init__.py
tech_smu_mcp_demo-0.1.0.dist-info/METADATA
tech_smu_mcp_demo-0.1.0.dist-info/WHEEL
tech_smu_mcp_demo-0.1.0.dist-info/entry_points.txt
tech_smu_mcp_demo-0.1.0.dist-info/RECORD
