Metadata-Version: 2.4
Name: tech-smu-mcp-demo
Version: 0.1.0
Summary: Add your description here
Author-email: Administrator <admin@example.com>
Requires-Python: >=3.13
Requires-Dist: mcp[cli]>=1.9.4
